{
  "Барц 01":     "8001",
  "Барц 02":     "8002",
  "Барц 03":     "8003",
  "Барц 04":     "8004",
  "Барц 05":     "8005",
  "Барц 06":     "8006",

  "Зигхард 05":  "8011",
  "Зигхард 06":  "8012",
  "Кайн 01":  "8013",
  "Кайн 02":  "8014",
  "Кайн 03":  "8015",
  "Кайн 04":  "8016",

  "Гастин 01":    "8031",
  "Гастин 02":    "8032",
  "Гастин 03":    "8033",
  "Гастин 04":    "8034",
  "Гастин 05":    "8035",
  "Гастин 06":    "8036",

  "Кастиен 05":    "8041",
  "Кастиен 06":    "8042",
  "Ария 01":    "8043",
  "Ария 02":    "8044",
  "Ария 03":    "8045",
  "Ария 04":    "8046"
}